spmflex/__init__.py
spmflex/driver.py
spmflex-0.1.1.dist-info/LICENSE
spmflex-0.1.1.dist-info/METADATA
spmflex-0.1.1.dist-info/WHEEL
spmflex-0.1.1.dist-info/entry_points.txt
spmflex-0.1.1.dist-info/top_level.txt
spmflex-0.1.1.dist-info/RECORD
