Metadata-Version: 2.1
Name: spmflex
Version: 0.1.1
Summary: Python driver for Honeywell SPM Flex gas dectectors.
Home-page: http://github.com/numat/spmflex/
Author: Patrick Fuller
Author-email: pat@numat-tech.com
License: GPLv2
Platform: UNKNOWN
Classifier: License :: OSI Approved :: GNU General Public License v2 (GPLv2)
Classifier: Development Status :: 4 - Beta
Classifier: Natural Language :: English
Classifier: Programming Language :: Python
Classifier: Programming Language :: Python :: 3
Classifier: Programming Language :: Python :: 3.5
Classifier: Programming Language :: Python :: 3.6
Classifier: Programming Language :: Python :: 3.7
Classifier: Topic :: Scientific/Engineering :: Human Machine Interfaces
Requires-Dist: aiohttp
Requires-Dist: xmltodict
